c7m/__init__.py
c7m/_nbdev.py
c7m/analyse_intensity.py
c7m/annotation_db.py
c7m/batch_process_segmentation.py
c7m/cellprofiler.py
c7m/denoise.py
c7m/dim_reduce.py
c7m/dimensionality_reduction.py
c7m/focus_stacking.py
c7m/image_analysis.py
c7m/load_bioformats_images.py
c7m/load_tiff_images.py
c7m/lobe_count_prediction.py
c7m/process_segmentation.py
c7m/qc.py
c7m-0.1.2.dist-info/LICENSE
c7m-0.1.2.dist-info/METADATA
c7m-0.1.2.dist-info/WHEEL
c7m-0.1.2.dist-info/entry_points.txt
c7m-0.1.2.dist-info/top_level.txt
c7m-0.1.2.dist-info/RECORD
