Metadata-Version: 2.1
Name: c7m
Version: 0.1.2
Summary: Module for analysis of high-throughput, fluorescence, wide-field microscopy images.
Home-page: https://github.com/mlippeve/c7m
Author: Maxim Lippeveld
Author-email: maxim.lippeveld@ugent.be
License: Apache Software License 2.0
Keywords: microscopy,segmentation,classification
Platform: UNKNOWN
Classifier: Development Status :: 2 - Pre-Alpha
Classifier: Intended Audience :: Developers
Classifier: License :: OSI Approved :: Apache Software License
Classifier: Natural Language :: English
Classifier: Programming Language :: Python :: 3.6
Classifier: Programming Language :: Python :: 3.7
Classifier: Programming Language :: Python :: 3.8
Requires-Python: >=3.6
Requires-Dist: scikit-image
Requires-Dist: scikit-learn
Requires-Dist: numpy (==1.15.4)
Requires-Dist: pandas
Requires-Dist: python-bioformats
Requires-Dist: python-dotenv
Requires-Dist: javabridge
Requires-Dist: matplotlib
Requires-Dist: opencv-python
Requires-Dist: tqdm
Requires-Dist: click
Requires-Dist: seaborn
